{
  "schema_version": "1.0.0",
  "event_id": "EV00057",
  "meta": {
    "symbol": "NQ1!",
    "timeframe": "5m",
    "timezone": "UTC",
    "created_at": "2025-12-07T03:53:12.297377Z"
  },
  "trade_signals": [
    {
      "signal": "buy_long",
      "fvg_5m_id": 57,
      "direction": "up",
      "index_first_touch": 1,
      "index_valid_close_after_touch": 1,
      "entry_ts": "2025-12-02T19:10:00Z",
      "entry_price": 25604.0,
      "stop_loss": 25587.25,
      "take_profit": 25620.75,
      "exit_signal": "sell_l_loss",
      "exit_ts": "2025-12-02 19:20:00",
      "exit_price": 25587.25
    }
  ],
  "hourly_fvg": {
    "fvg_hour_id": 4,
    "direction": "up",
    "start_time": "2025-12-02T13:00:00Z",
    "end_time": "2025-12-02T16:00:00Z",
    "begin_bound": 25514.75,
    "end_bound": 25531.0,
    "pretouch_window_start": "2025-12-02 16:00:00",
    "pretouch_window_end": "2025-12-02 19:00:00",
    "touch_ts": "2025-12-02 16:10:00",
    "touch_price": 25524.25,
    "touch_bound": 25531.0,
    "touch_candle_ts": "2025-12-02 16:10:00",
    "posttouch_window_start": "2025-12-02 16:10:00",
    "posttouch_window_end": "2025-12-02 19:10:00"
  },
  "fvg_5m": [
    {
      "fvg_5m_id": 57,
      "direction": "up",
      "start_time": "2025-12-02T18:55:00Z",
      "begin_bound": 25587.25,
      "end_bound": 25589.25,
      "index_first_touch": 1,
      "index_valid_close_after_touch": 1,
      "touch_ts": "2025-12-02T19:10:00Z",
      "entry_ts": "2025-12-02T19:10:00Z",
      "entry_price": 25604.0
    }
  ],
  "bos_5m": [
    {
      "bos_id": 83,
      "ts_event": "2025-12-02T16:15:00Z",
      "bos_direction": "bos_down",
      "trigger_close": 25529.75,
      "broken_level": 25531.0,
      "source_hilo_id": 188
    },
    {
      "bos_id": 84,
      "ts_event": "2025-12-02T16:20:00Z",
      "bos_direction": "bos_down",
      "trigger_close": 25462.5,
      "broken_level": 25531.0,
      "source_hilo_id": 188
    },
    {
      "bos_id": 85,
      "ts_event": "2025-12-02T16:25:00Z",
      "bos_direction": "bos_down",
      "trigger_close": 25459.75,
      "broken_level": 25531.0,
      "source_hilo_id": 188
    },
    {
      "bos_id": 86,
      "ts_event": "2025-12-02T16:30:00Z",
      "bos_direction": "bos_down",
      "trigger_close": 25449.5,
      "broken_level": 25531.0,
      "source_hilo_id": 188
    },
    {
      "bos_id": 87,
      "ts_event": "2025-12-02T16:35:00Z",
      "bos_direction": "bos_down",
      "trigger_close": 25501.75,
      "broken_level": 25531.0,
      "source_hilo_id": 188
    },
    {
      "bos_id": 88,
      "ts_event": "2025-12-02T17:00:00Z",
      "bos_direction": "bos_up",
      "trigger_close": 25535.5,
      "broken_level": 25534.25,
      "source_hilo_id": 204
    },
    {
      "bos_id": 89,
      "ts_event": "2025-12-02T17:15:00Z",
      "bos_direction": "bos_up",
      "trigger_close": 25594.0,
      "broken_level": 25554.25,
      "source_hilo_id": 206
    },
    {
      "bos_id": 90,
      "ts_event": "2025-12-02T17:20:00Z",
      "bos_direction": "bos_up",
      "trigger_close": 25583.75,
      "broken_level": 25554.25,
      "source_hilo_id": 206
    },
    {
      "bos_id": 91,
      "ts_event": "2025-12-02T17:30:00Z",
      "bos_direction": "bos_up",
      "trigger_close": 25611.5,
      "broken_level": 25607.25,
      "source_hilo_id": 209
    },
    {
      "bos_id": 92,
      "ts_event": "2025-12-02T17:50:00Z",
      "bos_direction": "bos_down",
      "trigger_close": 25562.5,
      "broken_level": 25579.0,
      "source_hilo_id": 210
    },
    {
      "bos_id": 93,
      "ts_event": "2025-12-02T17:55:00Z",
      "bos_direction": "bos_down",
      "trigger_close": 25506.25,
      "broken_level": 25579.0,
      "source_hilo_id": 210
    },
    {
      "bos_id": 94,
      "ts_event": "2025-12-02T18:00:00Z",
      "bos_direction": "bos_down",
      "trigger_close": 25535.25,
      "broken_level": 25579.0,
      "source_hilo_id": 210
    },
    {
      "bos_id": 95,
      "ts_event": "2025-12-02T18:35:00Z",
      "bos_direction": "bos_down",
      "trigger_close": 25536.0,
      "broken_level": 25539.25,
      "source_hilo_id": 220
    }
  ],
  "summary": {
    "fvg_5m_count": 1,
    "bos_5m_count": 13,
    "signal_count": 1,
    "status": "completed"
  },
  "ohlc_5m": [
    {
      "ts_event": "2025-12-02T13:00:00Z",
      "open": 25498.5,
      "high": 25499.5,
      "low": 25485.75,
      "close": 25493.25,
      "volume": 585.0,
      "is_rth_session": false
    },
    {
      "ts_event": "2025-12-02T13:05:00Z",
      "open": 25493.0,
      "high": 25495.0,
      "low": 25487.5,
      "close": 25492.75,
      "volume": 307.0,
      "is_rth_session": false
    },
    {
      "ts_event": "2025-12-02T13:10:00Z",
      "open": 25492.5,
      "high": 25501.0,
      "low": 25489.5,
      "close": 25498.75,
      "volume": 713.0,
      "is_rth_session": false
    },
    {
      "ts_event": "2025-12-02T13:15:00Z",
      "open": 25499.25,
      "high": 25505.25,
      "low": 25491.75,
      "close": 25493.5,
      "volume": 709.0,
      "is_rth_session": false
    },
    {
      "ts_event": "2025-12-02T13:20:00Z",
      "open": 25494.75,
      "high": 25502.5,
      "low": 25486.75,
      "close": 25500.5,
      "volume": 552.0,
      "is_rth_session": false
    },
    {
      "ts_event": "2025-12-02T13:25:00Z",
      "open": 25498.75,
      "high": 25502.25,
      "low": 25495.5,
      "close": 25495.75,
      "volume": 348.0,
      "is_rth_session": false
    },
    {
      "ts_event": "2025-12-02T13:30:00Z",
      "open": 25496.25,
      "high": 25498.0,
      "low": 25483.0,
      "close": 25489.25,
      "volume": 796.0,
      "is_rth_session": false
    },
    {
      "ts_event": "2025-12-02T13:35:00Z",
      "open": 25489.0,
      "high": 25500.5,
      "low": 25483.5,
      "close": 25500.5,
      "volume": 673.0,
      "is_rth_session": false
    },
    {
      "ts_event": "2025-12-02T13:40:00Z",
      "open": 25501.0,
      "high": 25514.75,
      "low": 25501.0,
      "close": 25507.5,
      "volume": 1390.0,
      "is_rth_session": false
    },
    {
      "ts_event": "2025-12-02T13:45:00Z",
      "open": 25506.5,
      "high": 25507.0,
      "low": 25486.0,
      "close": 25493.25,
      "volume": 1215.0,
      "is_rth_session": false
    },
    {
      "ts_event": "2025-12-02T13:50:00Z",
      "open": 25493.25,
      "high": 25496.75,
      "low": 25480.5,
      "close": 25492.5,
      "volume": 1175.0,
      "is_rth_session": false
    },
    {
      "ts_event": "2025-12-02T13:55:00Z",
      "open": 25492.5,
      "high": 25507.25,
      "low": 25485.5,
      "close": 25506.75,
      "volume": 1045.0,
      "is_rth_session": false
    },
    {
      "ts_event": "2025-12-02T14:00:00Z",
      "open": 25507.25,
      "high": 25522.5,
      "low": 25503.75,
      "close": 25517.25,
      "volume": 2342.0,
      "is_rth_session": false
    },
    {
      "ts_event": "2025-12-02T14:05:00Z",
      "open": 25517.5,
      "high": 25522.75,
      "low": 25507.25,
      "close": 25507.25,
      "volume": 1254.0,
      "is_rth_session": false
    },
    {
      "ts_event": "2025-12-02T14:10:00Z",
      "open": 25507.75,
      "high": 25513.5,
      "low": 25502.0,
      "close": 25508.75,
      "volume": 945.0,
      "is_rth_session": false
    },
    {
      "ts_event": "2025-12-02T14:15:00Z",
      "open": 25509.0,
      "high": 25514.25,
      "low": 25505.0,
      "close": 25509.75,
      "volume": 704.0,
      "is_rth_session": false
    },
    {
      "ts_event": "2025-12-02T14:20:00Z",
      "open": 25509.25,
      "high": 25515.25,
      "low": 25503.75,
      "close": 25511.25,
      "volume": 831.0,
      "is_rth_session": false
    },
    {
      "ts_event": "2025-12-02T14:25:00Z",
      "open": 25511.0,
      "high": 25511.0,
      "low": 25484.0,
      "close": 25492.25,
      "volume": 2817.0,
      "is_rth_session": false
    },
    {
      "ts_event": "2025-12-02T14:30:00Z",
      "open": 25492.75,
      "high": 25527.0,
      "low": 25471.25,
      "close": 25526.0,
      "volume": 14775.0,
      "is_rth_session": true
    },
    {
      "ts_event": "2025-12-02T14:35:00Z",
      "open": 25526.25,
      "high": 25608.75,
      "low": 25520.5,
      "close": 25597.0,
      "volume": 16490.0,
      "is_rth_session": true
    },
    {
      "ts_event": "2025-12-02T14:40:00Z",
      "open": 25597.25,
      "high": 25613.0,
      "low": 25575.75,
      "close": 25595.5,
      "volume": 10710.0,
      "is_rth_session": true
    },
    {
      "ts_event": "2025-12-02T14:45:00Z",
      "open": 25595.75,
      "high": 25604.25,
      "low": 25566.75,
      "close": 25583.25,
      "volume": 9300.0,
      "is_rth_session": true
    },
    {
      "ts_event": "2025-12-02T14:50:00Z",
      "open": 25583.5,
      "high": 25609.75,
      "low": 25562.0,
      "close": 25569.5,
      "volume": 9732.0,
      "is_rth_session": true
    },
    {
      "ts_event": "2025-12-02T14:55:00Z",
      "open": 25569.5,
      "high": 25605.5,
      "low": 25564.25,
      "close": 25597.75,
      "volume": 8073.0,
      "is_rth_session": true
    },
    {
      "ts_event": "2025-12-02T15:00:00Z",
      "open": 25598.5,
      "high": 25646.0,
      "low": 25595.0,
      "close": 25634.75,
      "volume": 11769.0,
      "is_rth_session": true
    },
    {
      "ts_event": "2025-12-02T15:05:00Z",
      "open": 25635.5,
      "high": 25654.75,
      "low": 25629.0,
      "close": 25637.75,
      "volume": 7728.0,
      "is_rth_session": true
    },
    {
      "ts_event": "2025-12-02T15:10:00Z",
      "open": 25638.25,
      "high": 25639.75,
      "low": 25603.5,
      "close": 25634.5,
      "volume": 8752.0,
      "is_rth_session": true
    },
    {
      "ts_event": "2025-12-02T15:15:00Z",
      "open": 25634.75,
      "high": 25644.5,
      "low": 25616.5,
      "close": 25627.75,
      "volume": 5441.0,
      "is_rth_session": true
    },
    {
      "ts_event": "2025-12-02T15:20:00Z",
      "open": 25627.5,
      "high": 25640.0,
      "low": 25605.75,
      "close": 25638.25,
      "volume": 6133.0,
      "is_rth_session": true
    },
    {
      "ts_event": "2025-12-02T15:25:00Z",
      "open": 25638.25,
      "high": 25647.25,
      "low": 25566.5,
      "close": 25573.25,
      "volume": 9593.0,
      "is_rth_session": true
    },
    {
      "ts_event": "2025-12-02T15:30:00Z",
      "open": 25573.25,
      "high": 25581.0,
      "low": 25531.0,
      "close": 25550.5,
      "volume": 13629.0,
      "is_rth_session": true
    },
    {
      "ts_event": "2025-12-02T15:35:00Z",
      "open": 25551.25,
      "high": 25571.25,
      "low": 25538.0,
      "close": 25557.75,
      "volume": 6854.0,
      "is_rth_session": true
    },
    {
      "ts_event": "2025-12-02T15:40:00Z",
      "open": 25559.5,
      "high": 25628.0,
      "low": 25555.0,
      "close": 25621.5,
      "volume": 7835.0,
      "is_rth_session": true
    },
    {
      "ts_event": "2025-12-02T15:45:00Z",
      "open": 25621.75,
      "high": 25650.25,
      "low": 25614.0,
      "close": 25650.0,
      "volume": 6517.0,
      "is_rth_session": true
    },
    {
      "ts_event": "2025-12-02T15:50:00Z",
      "open": 25650.5,
      "high": 25670.0,
      "low": 25645.25,
      "close": 25651.25,
      "volume": 8374.0,
      "is_rth_session": true
    },
    {
      "ts_event": "2025-12-02T15:55:00Z",
      "open": 25651.75,
      "high": 25660.75,
      "low": 25638.0,
      "close": 25647.75,
      "volume": 4346.0,
      "is_rth_session": true
    },
    {
      "ts_event": "2025-12-02T16:00:00Z",
      "open": 25648.0,
      "high": 25663.5,
      "low": 25620.0,
      "close": 25647.75,
      "volume": 8862.0,
      "is_rth_session": true
    },
    {
      "ts_event": "2025-12-02T16:05:00Z",
      "open": 25647.75,
      "high": 25648.5,
      "low": 25584.0,
      "close": 25592.75,
      "volume": 10944.0,
      "is_rth_session": true
    },
    {
      "ts_event": "2025-12-02T16:10:00Z",
      "open": 25593.25,
      "high": 25604.75,
      "low": 25524.25,
      "close": 25539.75,
      "volume": 12673.0,
      "is_rth_session": true
    },
    {
      "ts_event": "2025-12-02T16:15:00Z",
      "open": 25540.25,
      "high": 25553.75,
      "low": 25514.5,
      "close": 25529.75,
      "volume": 8859.0,
      "is_rth_session": true
    },
    {
      "ts_event": "2025-12-02T16:20:00Z",
      "open": 25529.5,
      "high": 25543.0,
      "low": 25459.0,
      "close": 25462.5,
      "volume": 10924.0,
      "is_rth_session": true
    },
    {
      "ts_event": "2025-12-02T16:25:00Z",
      "open": 25462.0,
      "high": 25484.25,
      "low": 25443.0,
      "close": 25459.75,
      "volume": 9789.0,
      "is_rth_session": true
    },
    {
      "ts_event": "2025-12-02T16:30:00Z",
      "open": 25459.5,
      "high": 25480.75,
      "low": 25414.5,
      "close": 25449.5,
      "volume": 12554.0,
      "is_rth_session": true
    },
    {
      "ts_event": "2025-12-02T16:35:00Z",
      "open": 25448.75,
      "high": 25502.75,
      "low": 25445.0,
      "close": 25501.75,
      "volume": 8193.0,
      "is_rth_session": true
    },
    {
      "ts_event": "2025-12-02T16:40:00Z",
      "open": 25502.0,
      "high": 25525.0,
      "low": 25488.25,
      "close": 25488.25,
      "volume": 6949.0,
      "is_rth_session": true
    },
    {
      "ts_event": "2025-12-02T16:45:00Z",
      "open": 25488.5,
      "high": 25510.75,
      "low": 25477.75,
      "close": 25495.75,
      "volume": 6185.0,
      "is_rth_session": true
    },
    {
      "ts_event": "2025-12-02T16:50:00Z",
      "open": 25495.5,
      "high": 25520.5,
      "low": 25490.0,
      "close": 25517.0,
      "volume": 5153.0,
      "is_rth_session": true
    },
    {
      "ts_event": "2025-12-02T16:55:00Z",
      "open": 25517.0,
      "high": 25534.25,
      "low": 25502.0,
      "close": 25509.25,
      "volume": 5513.0,
      "is_rth_session": true
    },
    {
      "ts_event": "2025-12-02T17:00:00Z",
      "open": 25509.75,
      "high": 25554.25,
      "low": 25504.5,
      "close": 25535.5,
      "volume": 6918.0,
      "is_rth_session": true
    },
    {
      "ts_event": "2025-12-02T17:05:00Z",
      "open": 25535.25,
      "high": 25545.75,
      "low": 25515.5,
      "close": 25518.0,
      "volume": 3677.0,
      "is_rth_session": true
    },
    {
      "ts_event": "2025-12-02T17:10:00Z",
      "open": 25517.5,
      "high": 25550.75,
      "low": 25514.75,
      "close": 25549.75,
      "volume": 3761.0,
      "is_rth_session": true
    },
    {
      "ts_event": "2025-12-02T17:15:00Z",
      "open": 25549.5,
      "high": 25599.25,
      "low": 25545.5,
      "close": 25594.0,
      "volume": 5857.0,
      "is_rth_session": true
    },
    {
      "ts_event": "2025-12-02T17:20:00Z",
      "open": 25594.5,
      "high": 25607.25,
      "low": 25579.0,
      "close": 25583.75,
      "volume": 5237.0,
      "is_rth_session": true
    },
    {
      "ts_event": "2025-12-02T17:25:00Z",
      "open": 25584.5,
      "high": 25613.75,
      "low": 25579.5,
      "close": 25603.75,
      "volume": 4076.0,
      "is_rth_session": true
    },
    {
      "ts_event": "2025-12-02T17:30:00Z",
      "open": 25604.25,
      "high": 25622.25,
      "low": 25604.25,
      "close": 25611.5,
      "volume": 3883.0,
      "is_rth_session": true
    },
    {
      "ts_event": "2025-12-02T17:35:00Z",
      "open": 25612.0,
      "high": 25612.75,
      "low": 25586.5,
      "close": 25596.75,
      "volume": 4707.0,
      "is_rth_session": true
    },
    {
      "ts_event": "2025-12-02T17:40:00Z",
      "open": 25597.0,
      "high": 25602.75,
      "low": 25584.0,
      "close": 25597.0,
      "volume": 3156.0,
      "is_rth_session": true
    },
    {
      "ts_event": "2025-12-02T17:45:00Z",
      "open": 25597.0,
      "high": 25608.0,
      "low": 25591.0,
      "close": 25601.5,
      "volume": 2638.0,
      "is_rth_session": true
    },
    {
      "ts_event": "2025-12-02T17:50:00Z",
      "open": 25602.0,
      "high": 25606.0,
      "low": 25552.5,
      "close": 25562.5,
      "volume": 5881.0,
      "is_rth_session": true
    },
    {
      "ts_event": "2025-12-02T17:55:00Z",
      "open": 25562.5,
      "high": 25565.25,
      "low": 25506.0,
      "close": 25506.25,
      "volume": 6479.0,
      "is_rth_session": true
    },
    {
      "ts_event": "2025-12-02T18:00:00Z",
      "open": 25505.5,
      "high": 25548.5,
      "low": 25496.5,
      "close": 25535.25,
      "volume": 6411.0,
      "is_rth_session": true
    },
    {
      "ts_event": "2025-12-02T18:05:00Z",
      "open": 25535.25,
      "high": 25578.25,
      "low": 25532.5,
      "close": 25557.25,
      "volume": 4123.0,
      "is_rth_session": true
    },
    {
      "ts_event": "2025-12-02T18:10:00Z",
      "open": 25557.25,
      "high": 25562.0,
      "low": 25539.25,
      "close": 25551.5,
      "volume": 3719.0,
      "is_rth_session": true
    },
    {
      "ts_event": "2025-12-02T18:15:00Z",
      "open": 25551.75,
      "high": 25567.75,
      "low": 25540.25,
      "close": 25564.0,
      "volume": 2998.0,
      "is_rth_session": true
    },
    {
      "ts_event": "2025-12-02T18:20:00Z",
      "open": 25563.75,
      "high": 25586.0,
      "low": 25559.0,
      "close": 25570.75,
      "volume": 3441.0,
      "is_rth_session": true
    },
    {
      "ts_event": "2025-12-02T18:25:00Z",
      "open": 25570.5,
      "high": 25572.5,
      "low": 25544.5,
      "close": 25563.75,
      "volume": 3997.0,
      "is_rth_session": true
    },
    {
      "ts_event": "2025-12-02T18:30:00Z",
      "open": 25563.0,
      "high": 25576.75,
      "low": 25546.25,
      "close": 25553.25,
      "volume": 3089.0,
      "is_rth_session": true
    },
    {
      "ts_event": "2025-12-02T18:35:00Z",
      "open": 25553.25,
      "high": 25555.25,
      "low": 25530.75,
      "close": 25536.0,
      "volume": 3390.0,
      "is_rth_session": true
    },
    {
      "ts_event": "2025-12-02T18:40:00Z",
      "open": 25536.0,
      "high": 25562.75,
      "low": 25530.0,
      "close": 25558.0,
      "volume": 3378.0,
      "is_rth_session": true
    },
    {
      "ts_event": "2025-12-02T18:45:00Z",
      "open": 25557.5,
      "high": 25567.25,
      "low": 25542.5,
      "close": 25561.75,
      "volume": 3022.0,
      "is_rth_session": true
    },
    {
      "ts_event": "2025-12-02T18:50:00Z",
      "open": 25561.75,
      "high": 25586.5,
      "low": 25552.0,
      "close": 25585.5,
      "volume": 3740.0,
      "is_rth_session": true
    },
    {
      "ts_event": "2025-12-02T18:55:00Z",
      "open": 25586.0,
      "high": 25587.25,
      "low": 25558.25,
      "close": 25577.0,
      "volume": 3328.0,
      "is_rth_session": true
    },
    {
      "ts_event": "2025-12-02T19:00:00Z",
      "open": 25577.25,
      "high": 25600.25,
      "low": 25564.5,
      "close": 25595.25,
      "volume": 3779.0,
      "is_rth_session": true
    },
    {
      "ts_event": "2025-12-02T19:05:00Z",
      "open": 25595.25,
      "high": 25609.25,
      "low": 25589.25,
      "close": 25595.5,
      "volume": 3170.0,
      "is_rth_session": true
    },
    {
      "ts_event": "2025-12-02T19:10:00Z",
      "open": 25596.25,
      "high": 25609.25,
      "low": 25588.0,
      "close": 25604.0,
      "volume": 2640.0,
      "is_rth_session": true
    },
    {
      "ts_event": "2025-12-02T19:15:00Z",
      "open": 25603.0,
      "high": 25610.25,
      "low": 25594.25,
      "close": 25596.5,
      "volume": 2333.0,
      "is_rth_session": true
    },
    {
      "ts_event": "2025-12-02T19:20:00Z",
      "open": 25597.5,
      "high": 25599.0,
      "low": 25563.25,
      "close": 25571.75,
      "volume": 3585.0,
      "is_rth_session": true
    },
    {
      "ts_event": "2025-12-02T19:25:00Z",
      "open": 25573.0,
      "high": 25586.75,
      "low": 25565.0,
      "close": 25585.25,
      "volume": 2817.0,
      "is_rth_session": true
    },
    {
      "ts_event": "2025-12-02T19:30:00Z",
      "open": 25584.75,
      "high": 25607.0,
      "low": 25580.75,
      "close": 25604.5,
      "volume": 3034.0,
      "is_rth_session": true
    },
    {
      "ts_event": "2025-12-02T19:35:00Z",
      "open": 25604.25,
      "high": 25611.0,
      "low": 25595.25,
      "close": 25603.25,
      "volume": 2411.0,
      "is_rth_session": true
    },
    {
      "ts_event": "2025-12-02T19:40:00Z",
      "open": 25603.5,
      "high": 25606.75,
      "low": 25578.5,
      "close": 25587.25,
      "volume": 2944.0,
      "is_rth_session": true
    },
    {
      "ts_event": "2025-12-02T19:45:00Z",
      "open": 25587.5,
      "high": 25612.0,
      "low": 25582.25,
      "close": 25603.0,
      "volume": 3014.0,
      "is_rth_session": true
    },
    {
      "ts_event": "2025-12-02T19:50:00Z",
      "open": 25603.75,
      "high": 25635.5,
      "low": 25599.0,
      "close": 25625.0,
      "volume": 4711.0,
      "is_rth_session": true
    },
    {
      "ts_event": "2025-12-02T19:55:00Z",
      "open": 25625.5,
      "high": 25643.0,
      "low": 25622.25,
      "close": 25633.75,
      "volume": 3925.0,
      "is_rth_session": true
    },
    {
      "ts_event": "2025-12-02T20:00:00Z",
      "open": 25634.0,
      "high": 25639.75,
      "low": 25615.0,
      "close": 25622.0,
      "volume": 3234.0,
      "is_rth_session": true
    },
    {
      "ts_event": "2025-12-02T20:05:00Z",
      "open": 25622.25,
      "high": 25629.0,
      "low": 25616.75,
      "close": 25627.5,
      "volume": 2189.0,
      "is_rth_session": true
    }
  ]
}